my_pandas/__init__.py
my_pandas/__main__.py
my_pandas/main.py
my_pandas-0.1.0.dist-info/METADATA
my_pandas-0.1.0.dist-info/WHEEL
my_pandas-0.1.0.dist-info/entry_points.txt
my_pandas-0.1.0.dist-info/RECORD
