Metadata-Version: 2.1
Name: my-pandas
Version: 0.1.0
Summary: 
Author: gaoxl85
Author-email: gaoxiaoliang123@126.com
Requires-Python: >=3.11,<4.0
Classifier: Programming Language :: Python :: 3
Classifier: Programming Language :: Python :: 3.11
Requires-Dist: typer[all] (>=0.9.0,<0.10.0)
